LICENSE
asynctools/__init__.py
asynctools/py.typed
python_asynctools-0.1.3.3.dist-info/LICENSE
python_asynctools-0.1.3.3.dist-info/METADATA
python_asynctools-0.1.3.3.dist-info/WHEEL
python_asynctools-0.1.3.3.dist-info/RECORD
